empanada/__init__.py
empanada/compute_pathway_abundance.py
empanada/data/KOvsPATHWAY_BACTERIAL_KEGG_2013_07_15.tab
empanada/examples/pathway_abundance_empanada.tab
empanada/examples/simulated_ko_relative_abundance.tab
empanada-0.0.3.data/scripts/run_empanada.py
empanada-0.0.3.data/scripts/test_empanada.py
empanada-0.0.3.dist-info/AUTHORS.rst
empanada-0.0.3.dist-info/LICENSE
empanada-0.0.3.dist-info/METADATA
empanada-0.0.3.dist-info/WHEEL
empanada-0.0.3.dist-info/top_level.txt
empanada-0.0.3.dist-info/RECORD
