Metadata-Version: 2.1
Name: empanada
Version: 0.0.3
Summary: EMPANADA: a tool for evidence-based assignment of genes to pathways in metagenomic data
Home-page: http://elbo.gs.washington.edu/software_empanada.html
Author: Ohad Manor
Author-email: omanor@gmail.com
License: UNKNOWN
Platform: UNKNOWN
Classifier: License :: Free for non-commercial use
Requires-Dist: NumPy (>=1.16.0)
Requires-Dist: pandas (>=0.14)
